hello.py
ojuara_abaporojucaiba-1.0.dist-info/METADATA
ojuara_abaporojucaiba-1.0.dist-info/WHEEL
ojuara_abaporojucaiba-1.0.dist-info/top_level.txt
ojuara_abaporojucaiba-1.0.dist-info/RECORD
