Metadata-Version: 2.1
Name: ojuara-abaporojucaiba
Version: 1.0
Summary: Brincando mais uma vez
Home-page: UNKNOWN
Author: Ojuara Abaporojucaíba
Author-email: ojuara@araujo.com
License: UNKNOWN
Platform: UNKNOWN
